{
    "type": "Program",
    "start": 0,
    "end": 172,
    "loc": {
        "start": {
            "line": 1,
            "column": 0
        },
        "end": {
            "line": 9,
            "column": 0
        }
    },
    "body": [
        {
            "type": "FunctionDeclaration",
            "start": 26,
            "end": 117,
            "loc": {
                "start": {
                    "line": 2,
                    "column": 0
                },
                "end": {
                    "line": 5,
                    "column": 1
                }
            },
            "id": {
                "type": "Identifier",
                "start": 35,
                "end": 48,
                "loc": {
                    "start": {
                        "line": 2,
                        "column": 9
                    },
                    "end": {
                        "line": 2,
                        "column": 22
                    }
                },
                "name": "calculateArea"
            },
            "expression": false,
            "generator": false,
            "async": false,
            "params": [
                {
                    "type": "Identifier",
                    "start": 49,
                    "end": 55,
                    "loc": {
                        "start": {
                            "line": 2,
                            "column": 23
                        },
                        "end": {
                            "line": 2,
                            "column": 29
                        }
                    },
                    "name": "radius"
                }
            ],
            "body": {
                "type": "BlockStatement",
                "start": 57,
                "end": 117,
                "loc": {
                    "start": {
                        "line": 2,
                        "column": 31
                    },
                    "end": {
                        "line": 5,
                        "column": 1
                    }
                },
                "body": [
                    {
                        "type": "VariableDeclaration",
                        "start": 63,
                        "end": 82,
                        "loc": {
                            "start": {
                                "line": 3,
                                "column": 4
                            },
                            "end": {
                                "line": 3,
                                "column": 23
                            }
                        },
                        "declarations": [
                            {
                                "type": "VariableDeclarator",
                                "start": 69,
                                "end": 81,
                                "loc": {
                                    "start": {
                                        "line": 3,
                                        "column": 10
                                    },
                                    "end": {
                                        "line": 3,
                                        "column": 22
                                    }
                                },
                                "id": {
                                    "type": "Identifier",
                                    "start": 69,
                                    "end": 71,
                                    "loc": {
                                        "start": {
                                            "line": 3,
                                            "column": 10
                                        },
                                        "end": {
                                            "line": 3,
                                            "column": 12
                                        }
                                    },
                                    "name": "PI"
                                },
                                "init": {
                                    "type": "Literal",
                                    "start": 74,
                                    "end": 81,
                                    "loc": {
                                        "start": {
                                            "line": 3,
                                            "column": 15
                                        },
                                        "end": {
                                            "line": 3,
                                            "column": 22
                                        }
                                    },
                                    "value": 3.14159,
                                    "raw": "3.14159"
                                }
                            }
                        ],
                        "kind": "const"
                    },
                    {
                        "type": "ReturnStatement",
                        "start": 87,
                        "end": 115,
                        "loc": {
                            "start": {
                                "line": 4,
                                "column": 4
                            },
                            "end": {
                                "line": 4,
                                "column": 32
                            }
                        },
                        "argument": {
                            "type": "BinaryExpression",
                            "start": 94,
                            "end": 114,
                            "loc": {
                                "start": {
                                    "line": 4,
                                    "column": 11
                                },
                                "end": {
                                    "line": 4,
                                    "column": 31
                                }
                            },
                            "left": {
                                "type": "BinaryExpression",
                                "start": 94,
                                "end": 105,
                                "loc": {
                                    "start": {
                                        "line": 4,
                                        "column": 11
                                    },
                                    "end": {
                                        "line": 4,
                                        "column": 22
                                    }
                                },
                                "left": {
                                    "type": "Identifier",
                                    "start": 94,
                                    "end": 96,
                                    "loc": {
                                        "start": {
                                            "line": 4,
                                            "column": 11
                                        },
                                        "end": {
                                            "line": 4,
                                            "column": 13
                                        }
                                    },
                                    "name": "PI"
                                },
                                "operator": "*",
                                "right": {
                                    "type": "Identifier",
                                    "start": 99,
                                    "end": 105,
                                    "loc": {
                                        "start": {
                                            "line": 4,
                                            "column": 16
                                        },
                                        "end": {
                                            "line": 4,
                                            "column": 22
                                        }
                                    },
                                    "name": "radius"
                                }
                            },
                            "operator": "*",
                            "right": {
                                "type": "Identifier",
                                "start": 108,
                                "end": 114,
                                "loc": {
                                    "start": {
                                        "line": 4,
                                        "column": 25
                                    },
                                    "end": {
                                        "line": 4,
                                        "column": 31
                                    }
                                },
                                "name": "radius"
                            }
                        }
                    }
                ]
            }
        },
        {
            "type": "VariableDeclaration",
            "start": 119,
            "end": 131,
            "loc": {
                "start": {
                    "line": 7,
                    "column": 0
                },
                "end": {
                    "line": 7,
                    "column": 12
                }
            },
            "declarations": [
                {
                    "type": "VariableDeclarator",
                    "start": 125,
                    "end": 130,
                    "loc": {
                        "start": {
                            "line": 7,
                            "column": 6
                        },
                        "end": {
                            "line": 7,
                            "column": 11
                        }
                    },
                    "id": {
                        "type": "Identifier",
                        "start": 125,
                        "end": 126,
                        "loc": {
                            "start": {
                                "line": 7,
                                "column": 6
                            },
                            "end": {
                                "line": 7,
                                "column": 7
                            }
                        },
                        "name": "r"
                    },
                    "init": {
                        "type": "Literal",
                        "start": 129,
                        "end": 130,
                        "loc": {
                            "start": {
                                "line": 7,
                                "column": 10
                            },
                            "end": {
                                "line": 7,
                                "column": 11
                            }
                        },
                        "value": 5,
                        "raw": "5"
                    }
                }
            ],
            "kind": "const"
        },
        {
            "type": "ExpressionStatement",
            "start": 132,
            "end": 171,
            "loc": {
                "start": {
                    "line": 8,
                    "column": 0
                },
                "end": {
                    "line": 8,
                    "column": 39
                }
            },
            "expression": {
                "type": "CallExpression",
                "start": 132,
                "end": 170,
                "loc": {
                    "start": {
                        "line": 8,
                        "column": 0
                    },
                    "end": {
                        "line": 8,
                        "column": 38
                    }
                },
                "callee": {
                    "type": "MemberExpression",
                    "start": 132,
                    "end": 143,
                    "loc": {
                        "start": {
                            "line": 8,
                            "column": 0
                        },
                        "end": {
                            "line": 8,
                            "column": 11
                        }
                    },
                    "object": {
                        "type": "Identifier",
                        "start": 132,
                        "end": 139,
                        "loc": {
                            "start": {
                                "line": 8,
                                "column": 0
                            },
                            "end": {
                                "line": 8,
                                "column": 7
                            }
                        },
                        "name": "console"
                    },
                    "property": {
                        "type": "Identifier",
                        "start": 140,
                        "end": 143,
                        "loc": {
                            "start": {
                                "line": 8,
                                "column": 8
                            },
                            "end": {
                                "line": 8,
                                "column": 11
                            }
                        },
                        "name": "log"
                    },
                    "computed": false,
                    "optional": false
                },
                "arguments": [
                    {
                        "type": "Literal",
                        "start": 144,
                        "end": 151,
                        "loc": {
                            "start": {
                                "line": 8,
                                "column": 12
                            },
                            "end": {
                                "line": 8,
                                "column": 19
                            }
                        },
                        "value": "Area:",
                        "raw": "\"Area:\""
                    },
                    {
                        "type": "CallExpression",
                        "start": 153,
                        "end": 169,
                        "loc": {
                            "start": {
                                "line": 8,
                                "column": 21
                            },
                            "end": {
                                "line": 8,
                                "column": 37
                            }
                        },
                        "callee": {
                            "type": "Identifier",
                            "start": 153,
                            "end": 166,
                            "loc": {
                                "start": {
                                    "line": 8,
                                    "column": 21
                                },
                                "end": {
                                    "line": 8,
                                    "column": 34
                                }
                            },
                            "name": "calculateArea"
                        },
                        "arguments": [
                            {
                                "type": "Identifier",
                                "start": 167,
                                "end": 168,
                                "loc": {
                                    "start": {
                                        "line": 8,
                                        "column": 35
                                    },
                                    "end": {
                                        "line": 8,
                                        "column": 36
                                    }
                                },
                                "name": "r"
                            }
                        ],
                        "optional": false
                    }
                ],
                "optional": false
            }
        }
    ],
    "sourceType": "script"
}